xsstrike/__init__.py
xsstrike/core/__init__.py
xsstrike/core/checker.py
xsstrike/core/colors.py
xsstrike/core/config.py
xsstrike/core/dom.py
xsstrike/core/encoders.py
xsstrike/core/filterChecker.py
xsstrike/core/fuzzer.py
xsstrike/core/generator.py
xsstrike/core/htmlParser.py
xsstrike/core/jsContexter.py
xsstrike/core/log.py
xsstrike/core/photon.py
xsstrike/core/prompt.py
xsstrike/core/requester.py
xsstrike/core/updater.py
xsstrike/core/utils.py
xsstrike/core/wafDetector.py
xsstrike/core/zetanize.py
xsstrike/db/definitions.json
xsstrike/db/wafSignatures.json
xsstrike/modes/__init__.py
xsstrike/modes/bruteforcer.py
xsstrike/modes/crawl.py
xsstrike/modes/scan.py
xsstrike/modes/singleFuzz.py
xsstrike/plugins/__init__.py
xsstrike/plugins/retireJs.py
xsstrike/test.html
xsstrike/xsstrikesback.py
xsstrike-3.2.1.dist-info/entry_points.txt
xsstrike-3.2.1.dist-info/LICENSE
xsstrike-3.2.1.dist-info/WHEEL
xsstrike-3.2.1.dist-info/METADATA
xsstrike-3.2.1.dist-info/RECORD
