Metadata-Version: 2.1
Name: xsstrike
Version: 3.2.1
Summary: XSStrike is a Cross Site Scripting detection suite equipped with four hand written parsers, an intelligent payload generator, a powerful fuzzing engine and an incredibly fast crawler. Instead of injecting payloads and checking it works like all the other tools do, XSStrike analyses the response with multiple parsers and then crafts payloads that are guaranteed to work by context analysis integrated with a fuzzing engine.
Home-page: https://github.com/rasheed-rd/XSStrike
License: GNU GPLv3
Keywords: xsstrike,cross site scripting,security
Author: Somdev Sangwan
Author-email: s0md3v@gmail.com
Requires-Python: >=3.8,<4.0
Classifier: License :: Other/Proprietary License
Classifier: Programming Language :: Python :: 3
Classifier: Programming Language :: Python :: 3.8
Classifier: Programming Language :: Python :: 3.9
Classifier: Programming Language :: Python :: 3.10
Classifier: Programming Language :: Python :: 3.11
Classifier: Topic :: Security
Requires-Dist: fuzzywuzzy
Requires-Dist: requests
Requires-Dist: tld
Project-URL: Repository, https://github.com/rasheed-rd/XSStrike
